Simulation-tools/Verilog/icarus/example-cli/trafic_lights.v
module trafic_lights(sa1, sa2, sb1, sb2,r,o,g);
input sa1;
input sa2;
input sb1;
input sb2;
output r;
output o;
output g;


assign r = (sa1 & sa2) | sb1;
assign o = sb1 | sa1;


endmodule

Simulation-tools/Verilog/icarus/example-cli/trafic_lights_tb.v
module trafic_lights_tb;

reg w_sa1;
reg w_sa2;
reg w_sb1;
reg w_sb2;


reg [3:0] test_data[0:16];

integer idx;
initial begin
    for(idx=0;idx<=16;idx=idx+1) begin
        test_data[idx]=idx;
    end
end


trafic_lights dut(
                .sa1(w_sa1),
                .sa2(w_sa2),
                .sb1(w_sb1),
                .sb2(w_sb2),
                .r(w_r),
                .o(w_o),
                .g(w_g));

integer i;
initial begin
    $dumpfile("trafic_lights_tb.vcd"); 
    $dumpvars (0,trafic_lights_tb);

    for(i=0;i <= 16;i=i+1) begin
        #10 {w_sa1,w_sa2,w_sb1,w_sb2} = test_data[i];
    end
    $display("Simulation finished!");
    $finish;
end



endmodule

Simulation-tools/Verilog/verilator/example-cli/trafic_lights_tb.vcd
$version Generated by VerilatedVcd $end
$timescale 1ps $end
 $scope module $rootio $end
 $upscope $end
 $scope module trafic_lights_tb $end
  $var wire 1 5 w_sa1 $end
  $var wire 1 6 w_sa2 $end
  $var wire 1 7 w_sb1 $end
  $var wire 1 8 w_sb2 $end
  $var wire 4 # test_data[0] [3:0] $end
  $var wire 4 $ test_data[1] [3:0] $end
  $var wire 4 % test_data[2] [3:0] $end
  $var wire 4 & test_data[3] [3:0] $end
  $var wire 4 ' test_data[4] [3:0] $end
  $var wire 4 ( test_data[5] [3:0] $end
  $var wire 4 ) test_data[6] [3:0] $end
  $var wire 4 * test_data[7] [3:0] $end
  $var wire 4 + test_data[8] [3:0] $end
  $var wire 4 , test_data[9] [3:0] $end
  $var wire 4 - test_data[10] [3:0] $end
  $var wire 4 . test_data[11] [3:0] $end
  $var wire 4 / test_data[12] [3:0] $end
  $var wire 4 0 test_data[13] [3:0] $end
  $var wire 4 1 test_data[14] [3:0] $end
  $var wire 4 2 test_data[15] [3:0] $end
  $var wire 4 3 test_data[16] [3:0] $end
  $var wire 32 4 idx [31:0] $end
  $var wire 1 9 w_r $end
  $var wire 1 : w_o $end
  $var wire 1 < w_g $end
  $var wire 32 ; i [31:0] $end
  $scope module dut $end
   $var wire 1 5 sa1 $end
   $var wire 1 6 sa2 $end
   $var wire 1 7 sb1 $end
   $var wire 1 8 sb2 $end
   $var wire 1 9 r $end
   $var wire 1 : o $end
   $var wire 1 < g $end
  $upscope $end
 $upscope $end
$enddefinitions $end


#0
b0000 #
b0001 $
b0010 %
b0011 &
b0100 '
b0101 (
b0110 )
b0111 *
b1000 +
b1001 ,
b1010 -
b1011 .
b1100 /
b1101 0
b1110 1
b1111 2
b0000 3
b00000000000000000000000000010001 4
05
06
07
08
09
0:
b00000000000000000000000000000000 ;
0<
#10
b00000000000000000000000000000001 ;
#20
18
b00000000000000000000000000000010 ;
#30
17
08
19
1:
b00000000000000000000000000000011 ;
#40
18
b00000000000000000000000000000100 ;
#50
16
07
08
09
0:
b00000000000000000000000000000101 ;
#60
18
b00000000000000000000000000000110 ;
#70
17
08
19
1:
b00000000000000000000000000000111 ;
#80
18
b00000000000000000000000000001000 ;
#90
15
06
07
08
09
b00000000000000000000000000001001 ;
#100
18
b00000000000000000000000000001010 ;
#110
17
08
19
b00000000000000000000000000001011 ;
#120
18
b00000000000000000000000000001100 ;
#130
16
07
08
b00000000000000000000000000001101 ;
#140
18
b00000000000000000000000000001110 ;
#150
17
08
b00000000000000000000000000001111 ;
#160
18
b00000000000000000000000000010000 ;
#170
05
06
07
08
09
0:
b00000000000000000000000000010001 ;
